odoo10_addon_purchase_line_product_image-10.0.1.0.0-py2.7-nspkg.pth
odoo/addons/purchase_line_product_image/README.rst
odoo/addons/purchase_line_product_image/__init__.py
odoo/addons/purchase_line_product_image/__manifest__.py
odoo/addons/purchase_line_product_image/models/__init__.py
odoo/addons/purchase_line_product_image/models/purchase_order.py
odoo/addons/purchase_line_product_image/static/description/icon.png
odoo/addons/purchase_line_product_image/static/src/xml/widget.xml
odoo/addons/purchase_line_product_image/views/purchase_order_views.xml
odoo10_addon_purchase_line_product_image-10.0.1.0.0.dist-info/DESCRIPTION.rst
odoo10_addon_purchase_line_product_image-10.0.1.0.0.dist-info/METADATA
odoo10_addon_purchase_line_product_image-10.0.1.0.0.dist-info/RECORD
odoo10_addon_purchase_line_product_image-10.0.1.0.0.dist-info/WHEEL
odoo10_addon_purchase_line_product_image-10.0.1.0.0.dist-info/metadata.json
odoo10_addon_purchase_line_product_image-10.0.1.0.0.dist-info/namespace_packages.txt
odoo10_addon_purchase_line_product_image-10.0.1.0.0.dist-info/top_level.txt
